dhruv13x/__init__.py
dhruv13x/cli.py
dhruv13x/version.py
dhruv13x-0.8.0.dist-info/METADATA
dhruv13x-0.8.0.dist-info/WHEEL
dhruv13x-0.8.0.dist-info/entry_points.txt
dhruv13x-0.8.0.dist-info/RECORD
